{
  "userProfilePK": 58868684,
  "calendarDate": "2026-02-03",
  "startTimestampGMT": "2026-02-02T21:00:00.0",
  "endTimestampGMT": "2026-02-03T21:00:00.0",
  "startTimestampLocal": "2026-02-03T00:00:00.0",
  "endTimestampLocal": "2026-02-04T00:00:00.0",
  "maxStressLevel": 96,
  "avgStressLevel": 27,
  "stressChartValueOffset": 1,
  "stressChartYAxisOrigin": -1,
  "stressValueDescriptorsDTOList": [
    {
      "key": "timestamp",
      "index": 0
    },
    {
      "key": "stressLevel",
      "index": 1
    }
  ],
  "stressValuesArray": [
    [
      1770066000000,
      39
    ],
    [
      1770066180000,
      37
    ],
    [
      1770066360000,
      40
    ],
    [
      1770066540000,
      48
    ],
    [
      1770066720000,
      29
    ],
    [
      1770066900000,
      23
    ],
    [
      1770067080000,
      31
    ],
    [
      1770067260000,
      32
    ],
    [
      1770067440000,
      27
    ],
    [
      1770067620000,
      30
    ],
    [
      1770067800000,
      30
    ],
    [
      1770067980000,
      28
    ],
    [
      1770068160000,
      32
    ],
    [
      1770068340000,
      24
    ],
    [
      1770068520000,
      25
    ],
    [
      1770068700000,
      25
    ],
    [
      1770068880000,
      21
    ],
    [
      1770069060000,
      22
    ],
    [
      1770069240000,
      25
    ],
    [
      1770069420000,
      25
    ],
    [
      1770069600000,
      22
    ],
    [
      1770069780000,
      25
    ],
    [
      1770069960000,
      40
    ],
    [
      1770070140000,
      52
    ],
    [
      1770070320000,
      47
    ],
    [
      1770070500000,
      45
    ],
    [
      1770070680000,
      72
    ],
    [
      1770070860000,
      24
    ],
    [
      1770071040000,
      24
    ],
    [
      1770071220000,
      25
    ],
    [
      1770071400000,
      20
    ],
    [
      1770071580000,
      24
    ],
    [
      1770071760000,
      23
    ],
    [
      1770071940000,
      12
    ],
    [
      1770072120000,
      31
    ],
    [
      1770072300000,
      24
    ],
    [
      1770072480000,
      20
    ],
    [
      1770072660000,
      18
    ],
    [
      1770072840000,
      19
    ],
    [
      1770073020000,
      -1
    ],
    [
      1770073200000,
      23
    ],
    [
      1770073380000,
      18
    ],
    [
      1770073560000,
      6
    ],
    [
      1770073740000,
      10
    ],
    [
      1770073920000,
      16
    ],
    [
      1770074100000,
      6
    ],
    [
      1770074280000,
      7
    ],
    [
      1770074460000,
      8
    ],
    [
      1770074640000,
      7
    ],
    [
      1770074820000,
      9
    ],
    [
      1770075000000,
      6
    ],
    [
      1770075180000,
      7
    ],
    [
      1770075360000,
      8
    ],
    [
      1770075540000,
      9
    ],
    [
      1770075720000,
      8
    ],
    [
      1770075900000,
      10
    ],
    [
      1770076080000,
      11
    ],
    [
      1770076260000,
      19
    ],
    [
      1770076440000,
      24
    ],
    [
      1770076620000,
      29
    ],
    [
      1770076800000,
      16
    ],
    [
      1770076980000,
      13
    ],
    [
      1770077160000,
      14
    ],
    [
      1770077340000,
      10
    ],
    [
      1770077520000,
      10
    ],
    [
      1770077700000,
      10
    ],
    [
      1770077880000,
      10
    ],
    [
      1770078060000,
      10
    ],
    [
      1770078240000,
      10
    ],
    [
      1770078420000,
      9
    ],
    [
      1770078600000,
      9
    ],
    [
      1770078780000,
      10
    ],
    [
      1770078960000,
      10
    ],
    [
      1770079140000,
      9
    ],
    [
      1770079320000,
      8
    ],
    [
      1770079500000,
      9
    ],
    [
      1770079680000,
      9
    ],
    [
      1770079860000,
      9
    ],
    [
      1770080040000,
      9
    ],
    [
      1770080220000,
      9
    ],
    [
      1770080400000,
      7
    ],
    [
      1770080580000,
      3
    ],
    [
      1770080760000,
      5
    ],
    [
      1770080940000,
      5
    ],
    [
      1770081120000,
      5
    ],
    [
      1770081300000,
      5
    ],
    [
      1770081480000,
      5
    ],
    [
      1770081660000,
      5
    ],
    [
      1770081840000,
      5
    ],
    [
      1770082020000,
      16
    ],
    [
      1770082200000,
      19
    ],
    [
      1770082380000,
      22
    ],
    [
      1770082560000,
      25
    ],
    [
      1770082740000,
      18
    ],
    [
      1770082920000,
      16
    ],
    [
      1770083100000,
      15
    ],
    [
      1770083280000,
      16
    ],
    [
      1770083460000,
      15
    ],
    [
      1770083640000,
      11
    ],
    [
      1770083820000,
      10
    ],
    [
      1770084000000,
      7
    ],
    [
      1770084180000,
      7
    ],
    [
      1770084360000,
      12
    ],
    [
      1770084540000,
      11
    ],
    [
      1770084720000,
      11
    ],
    [
      1770084900000,
      11
    ],
    [
      1770085080000,
      11
    ],
    [
      1770085260000,
      12
    ],
    [
      1770085440000,
      11
    ],
    [
      1770085620000,
      11
    ],
    [
      1770085800000,
      11
    ],
    [
      1770085980000,
      17
    ],
    [
      1770086160000,
      15
    ],
    [
      1770086340000,
      17
    ],
    [
      1770086520000,
      15
    ],
    [
      1770086700000,
      18
    ],
    [
      1770086880000,
      17
    ],
    [
      1770087060000,
      14
    ],
    [
      1770087240000,
      17
    ],
    [
      1770087420000,
      16
    ],
    [
      1770087600000,
      15
    ],
    [
      1770087780000,
      13
    ],
    [
      1770087960000,
      11
    ],
    [
      1770088140000,
      6
    ],
    [
      1770088320000,
      5
    ],
    [
      1770088500000,
      6
    ],
    [
      1770088680000,
      6
    ],
    [
      1770088860000,
      9
    ],
    [
      1770089040000,
      7
    ],
    [
      1770089220000,
      8
    ],
    [
      1770089400000,
      6
    ],
    [
      1770089580000,
      6
    ],
    [
      1770089760000,
      9
    ],
    [
      1770089940000,
      8
    ],
    [
      1770090120000,
      9
    ],
    [
      1770090300000,
      8
    ],
    [
      1770090480000,
      7
    ],
    [
      1770090660000,
      5
    ],
    [
      1770090840000,
      9
    ],
    [
      1770091020000,
      6
    ],
    [
      1770091200000,
      6
    ],
    [
      1770091380000,
      10
    ],
    [
      1770091560000,
      2
    ],
    [
      1770091740000,
      8
    ],
    [
      1770091920000,
      16
    ],
    [
      1770092100000,
      17
    ],
    [
      1770092280000,
      17
    ],
    [
      1770092460000,
      12
    ],
    [
      1770092640000,
      7
    ],
    [
      1770092820000,
      7
    ],
    [
      1770093000000,
      17
    ],
    [
      1770093180000,
      13
    ],
    [
      1770093360000,
      14
    ],
    [
      1770093540000,
      16
    ],
    [
      1770093720000,
      15
    ],
    [
      1770093900000,
      15
    ],
    [
      1770094080000,
      10
    ],
    [
      1770094260000,
      8
    ],
    [
      1770094440000,
      12
    ],
    [
      1770094620000,
      7
    ],
    [
      1770094800000,
      7
    ],
    [
      1770094980000,
      7
    ],
    [
      1770095160000,
      9
    ],
    [
      1770095340000,
      9
    ],
    [
      1770095520000,
      9
    ],
    [
      1770095700000,
      8
    ],
    [
      1770095880000,
      10
    ],
    [
      1770096060000,
      11
    ],
    [
      1770096240000,
      11
    ],
    [
      1770096420000,
      9
    ],
    [
      1770096600000,
      9
    ],
    [
      1770096780000,
      10
    ],
    [
      1770096960000,
      11
    ],
    [
      1770097140000,
      10
    ],
    [
      1770097320000,
      11
    ],
    [
      1770097500000,
      19
    ],
    [
      1770097680000,
      21
    ],
    [
      1770097860000,
      16
    ],
    [
      1770098040000,
      15
    ],
    [
      1770098220000,
      11
    ],
    [
      1770098400000,
      13
    ],
    [
      1770098580000,
      20
    ],
    [
      1770098760000,
      21
    ],
    [
      1770098940000,
      16
    ],
    [
      1770099120000,
      8
    ],
    [
      1770099300000,
      14
    ],
    [
      1770099480000,
      16
    ],
    [
      1770099660000,
      17
    ],
    [
      1770099840000,
      15
    ],
    [
      1770100020000,
      18
    ],
    [
      1770100200000,
      17
    ],
    [
      1770100380000,
      11
    ],
    [
      1770100560000,
      12
    ],
    [
      1770100740000,
      13
    ],
    [
      1770100920000,
      8
    ],
    [
      1770101100000,
      10
    ],
    [
      1770101280000,
      10
    ],
    [
      1770101460000,
      9
    ],
    [
      1770101640000,
      8
    ],
    [
      1770101820000,
      10
    ],
    [
      1770102000000,
      12
    ],
    [
      1770102180000,
      13
    ],
    [
      1770102360000,
      11
    ],
    [
      1770102540000,
      17
    ],
    [
      1770102720000,
      19
    ],
    [
      1770102900000,
      19
    ],
    [
      1770103080000,
      23
    ],
    [
      1770103260000,
      19
    ],
    [
      1770103440000,
      18
    ],
    [
      1770103620000,
      19
    ],
    [
      1770103800000,
      21
    ],
    [
      1770103980000,
      19
    ],
    [
      1770104160000,
      13
    ],
    [
      1770104340000,
      14
    ],
    [
      1770104520000,
      18
    ],
    [
      1770104700000,
      17
    ],
    [
      1770104880000,
      18
    ],
    [
      1770105060000,
      13
    ],
    [
      1770105240000,
      -1
    ],
    [
      1770105420000,
      67
    ],
    [
      1770105600000,
      25
    ],
    [
      1770105780000,
      10
    ],
    [
      1770105960000,
      24
    ],
    [
      1770106140000,
      34
    ],
    [
      1770106320000,
      34
    ],
    [
      1770106500000,
      33
    ],
    [
      1770106680000,
      27
    ],
    [
      1770106860000,
      33
    ],
    [
      1770107040000,
      25
    ],
    [
      1770107220000,
      24
    ],
    [
      1770107400000,
      28
    ],
    [
      1770107580000,
      34
    ],
    [
      1770107760000,
      25
    ],
    [
      1770107940000,
      21
    ],
    [
      1770108120000,
      23
    ],
    [
      1770108300000,
      23
    ],
    [
      1770108480000,
      23
    ],
    [
      1770108660000,
      24
    ],
    [
      1770108840000,
      24
    ],
    [
      1770109020000,
      25
    ],
    [
      1770109200000,
      25
    ],
    [
      1770109380000,
      11
    ],
    [
      1770109560000,
      22
    ],
    [
      1770109740000,
      22
    ],
    [
      1770109920000,
      21
    ],
    [
      1770110100000,
      20
    ],
    [
      1770110280000,
      21
    ],
    [
      1770110460000,
      20
    ],
    [
      1770110640000,
      22
    ],
    [
      1770110820000,
      25
    ],
    [
      1770111000000,
      28
    ],
    [
      1770111180000,
      21
    ],
    [
      1770111360000,
      21
    ],
    [
      1770111540000,
      32
    ],
    [
      1770111720000,
      16
    ],
    [
      1770111900000,
      21
    ],
    [
      1770112080000,
      25
    ],
    [
      1770112260000,
      28
    ],
    [
      1770112440000,
      23
    ],
    [
      1770112620000,
      27
    ],
    [
      1770112800000,
      25
    ],
    [
      1770112980000,
      25
    ],
    [
      1770113160000,
      20
    ],
    [
      1770113340000,
      35
    ],
    [
      1770113520000,
      29
    ],
    [
      1770113700000,
      30
    ],
    [
      1770113880000,
      37
    ],
    [
      1770114060000,
      37
    ],
    [
      1770114240000,
      45
    ],
    [
      1770114420000,
      64
    ],
    [
      1770114600000,
      52
    ],
    [
      1770114780000,
      42
    ],
    [
      1770114960000,
      46
    ],
    [
      1770115140000,
      61
    ],
    [
      1770115320000,
      52
    ],
    [
      1770115500000,
      39
    ],
    [
      1770115680000,
      43
    ],
    [
      1770115860000,
      36
    ],
    [
      1770116040000,
      32
    ],
    [
      1770116220000,
      34
    ],
    [
      1770116400000,
      55
    ],
    [
      1770116580000,
      35
    ],
    [
      1770116760000,
      63
    ],
    [
      1770116940000,
      23
    ],
    [
      1770117120000,
      55
    ],
    [
      1770117300000,
      40
    ],
    [
      1770117480000,
      55
    ],
    [
      1770117660000,
      37
    ],
    [
      1770117840000,
      34
    ],
    [
      1770118020000,
      39
    ],
    [
      1770118200000,
      30
    ],
    [
      1770118380000,
      42
    ],
    [
      1770118560000,
      40
    ],
    [
      1770118740000,
      40
    ],
    [
      1770118920000,
      32
    ],
    [
      1770119100000,
      34
    ],
    [
      1770119280000,
      37
    ],
    [
      1770119460000,
      43
    ],
    [
      1770119640000,
      44
    ],
    [
      1770119820000,
      43
    ],
    [
      1770120000000,
      35
    ],
    [
      1770120180000,
      31
    ],
    [
      1770120360000,
      27
    ],
    [
      1770120540000,
      49
    ],
    [
      1770120720000,
      40
    ],
    [
      1770120900000,
      59
    ],
    [
      1770121080000,
      37
    ],
    [
      1770121260000,
      39
    ],
    [
      1770121440000,
      30
    ],
    [
      1770121620000,
      39
    ],
    [
      1770121800000,
      48
    ],
    [
      1770121980000,
      32
    ],
    [
      1770122160000,
      37
    ],
    [
      1770122340000,
      39
    ],
    [
      1770122520000,
      57
    ],
    [
      1770122700000,
      31
    ],
    [
      1770122880000,
      31
    ],
    [
      1770123060000,
      43
    ],
    [
      1770123240000,
      55
    ],
    [
      1770123420000,
      48
    ],
    [
      1770123600000,
      36
    ],
    [
      1770123780000,
      25
    ],
    [
      1770123960000,
      36
    ],
    [
      1770124140000,
      76
    ],
    [
      1770124320000,
      -2
    ],
    [
      1770124500000,
      -2
    ],
    [
      1770124680000,
      -2
    ],
    [
      1770124860000,
      -2
    ],
    [
      1770125040000,
      -1
    ],
    [
      1770125220000,
      90
    ],
    [
      1770125400000,
      92
    ],
    [
      1770125580000,
      70
    ],
    [
      1770125760000,
      36
    ],
    [
      1770125940000,
      20
    ],
    [
      1770126120000,
      20
    ],
    [
      1770126300000,
      43
    ],
    [
      1770126480000,
      -2
    ],
    [
      1770126660000,
      78
    ],
    [
      1770126840000,
      22
    ],
    [
      1770127020000,
      28
    ],
    [
      1770127200000,
      49
    ],
    [
      1770127380000,
      46
    ],
    [
      1770127560000,
      57
    ],
    [
      1770127740000,
      39
    ],
    [
      1770127920000,
      37
    ],
    [
      1770128100000,
      45
    ],
    [
      1770128280000,
      56
    ],
    [
      1770128460000,
      43
    ],
    [
      1770128640000,
      48
    ],
    [
      1770128820000,
      45
    ],
    [
      1770129000000,
      41
    ],
    [
      1770129180000,
      37
    ],
    [
      1770129360000,
      60
    ],
    [
      1770129540000,
      56
    ],
    [
      1770129720000,
      51
    ],
    [
      1770129900000,
      43
    ],
    [
      1770130080000,
      52
    ],
    [
      1770130260000,
      63
    ],
    [
      1770130440000,
      54
    ],
    [
      1770130620000,
      40
    ],
    [
      1770130800000,
      65
    ],
    [
      1770130980000,
      44
    ],
    [
      1770131160000,
      40
    ],
    [
      1770131340000,
      49
    ],
    [
      1770131520000,
      41
    ],
    [
      1770131700000,
      37
    ],
    [
      1770131880000,
      35
    ],
    [
      1770132060000,
      28
    ],
    [
      1770132240000,
      52
    ],
    [
      1770132420000,
      38
    ],
    [
      1770132600000,
      45
    ],
    [
      1770132780000,
      25
    ],
    [
      1770132960000,
      25
    ],
    [
      1770133140000,
      31
    ],
    [
      1770133320000,
      31
    ],
    [
      1770133500000,
      51
    ],
    [
      1770133680000,
      41
    ],
    [
      1770133860000,
      60
    ],
    [
      1770134040000,
      36
    ],
    [
      1770134220000,
      37
    ],
    [
      1770134400000,
      40
    ],
    [
      1770134580000,
      40
    ],
    [
      1770134760000,
      42
    ],
    [
      1770134940000,
      40
    ],
    [
      1770135120000,
      29
    ],
    [
      1770135300000,
      33
    ],
    [
      1770135480000,
      30
    ],
    [
      1770135660000,
      35
    ],
    [
      1770135840000,
      27
    ],
    [
      1770136020000,
      40
    ],
    [
      1770136200000,
      43
    ],
    [
      1770136380000,
      36
    ],
    [
      1770136560000,
      -1
    ],
    [
      1770136740000,
      31
    ],
    [
      1770136920000,
      32
    ],
    [
      1770137100000,
      38
    ],
    [
      1770137280000,
      34
    ],
    [
      1770137460000,
      44
    ],
    [
      1770137640000,
      30
    ],
    [
      1770137820000,
      34
    ],
    [
      1770138000000,
      38
    ],
    [
      1770138180000,
      37
    ],
    [
      1770138360000,
      60
    ],
    [
      1770138540000,
      34
    ],
    [
      1770138720000,
      45
    ],
    [
      1770138900000,
      23
    ],
    [
      1770139080000,
      25
    ],
    [
      1770139260000,
      28
    ],
    [
      1770139440000,
      23
    ],
    [
      1770139620000,
      23
    ],
    [
      1770139800000,
      30
    ],
    [
      1770139980000,
      23
    ],
    [
      1770140160000,
      -2
    ],
    [
      1770140340000,
      -1
    ],
    [
      1770140520000,
      14
    ],
    [
      1770140700000,
      17
    ],
    [
      1770140880000,
      25
    ],
    [
      1770141060000,
      33
    ],
    [
      1770141240000,
      -1
    ],
    [
      1770141420000,
      -2
    ],
    [
      1770141600000,
      -2
    ],
    [
      1770141780000,
      -1
    ],
    [
      1770141960000,
      -1
    ],
    [
      1770142140000,
      84
    ],
    [
      1770142320000,
      60
    ],
    [
      1770142500000,
      40
    ],
    [
      1770142680000,
      67
    ],
    [
      1770142860000,
      -1
    ],
    [
      1770143040000,
      -2
    ],
    [
      1770143220000,
      -2
    ],
    [
      1770143400000,
      -2
    ],
    [
      1770143580000,
      -2
    ],
    [
      1770143760000,
      -2
    ],
    [
      1770143940000,
      -2
    ],
    [
      1770144120000,
      -2
    ],
    [
      1770144300000,
      84
    ],
    [
      1770144480000,
      -1
    ],
    [
      1770144660000,
      -2
    ],
    [
      1770144840000,
      -2
    ],
    [
      1770145020000,
      -2
    ],
    [
      1770145200000,
      93
    ],
    [
      1770145380000,
      66
    ],
    [
      1770145560000,
      40
    ],
    [
      1770145740000,
      33
    ],
    [
      1770145920000,
      33
    ],
    [
      1770146100000,
      43
    ],
    [
      1770146280000,
      45
    ],
    [
      1770146460000,
      38
    ],
    [
      1770146640000,
      40
    ],
    [
      1770146820000,
      34
    ],
    [
      1770147000000,
      46
    ],
    [
      1770147180000,
      47
    ],
    [
      1770147360000,
      56
    ],
    [
      1770147540000,
      59
    ],
    [
      1770147720000,
      40
    ],
    [
      1770147900000,
      37
    ],
    [
      1770148080000,
      32
    ],
    [
      1770148260000,
      31
    ],
    [
      1770148440000,
      30
    ],
    [
      1770148620000,
      40
    ],
    [
      1770148800000,
      46
    ],
    [
      1770148980000,
      32
    ],
    [
      1770149160000,
      28
    ],
    [
      1770149340000,
      30
    ],
    [
      1770149520000,
      25
    ],
    [
      1770149700000,
      38
    ],
    [
      1770149880000,
      55
    ],
    [
      1770150060000,
      36
    ],
    [
      1770150240000,
      43
    ],
    [
      1770150420000,
      42
    ],
    [
      1770150600000,
      58
    ],
    [
      1770150780000,
      51
    ],
    [
      1770150960000,
      43
    ],
    [
      1770151140000,
      43
    ],
    [
      1770151320000,
      52
    ],
    [
      1770151500000,
      25
    ],
    [
      1770151680000,
      27
    ],
    [
      1770151860000,
      32
    ],
    [
      1770152040000,
      29
    ],
    [
      1770152220000,
      54
    ]
  ],
  "bodyBatteryValueDescriptorsDTOList": [
    {
      "bodyBatteryValueDescriptorIndex": 0,
      "bodyBatteryValueDescriptorKey": "timestamp"
    },
    {
      "bodyBatteryValueDescriptorIndex": 1,
      "bodyBatteryValueDescriptorKey": "bodyBatteryStatus"
    },
    {
      "bodyBatteryValueDescriptorIndex": 2,
      "bodyBatteryValueDescriptorKey": "bodyBatteryLevel"
    },
    {
      "bodyBatteryValueDescriptorIndex": 3,
      "bodyBatteryValueDescriptorKey": "bodyBatteryVersion"
    }
  ],
  "bodyBatteryValuesArray": [
    [
      1770066000000,
      "MEASURED",
      10,
      3.0
    ],
    [
      1770066180000,
      "MEASURED",
      10,
      3.0
    ],
    [
      1770066360000,
      "MEASURED",
      10,
      3.0
    ],
    [
      1770066540000,
      "MEASURED",
      10,
      3.0
    ],
    [
      1770066720000,
      "MEASURED",
      10,
      3.0
    ],
    [
      1770066900000,
      "MEASURED",
      10,
      3.0
    ],
    [
      1770067080000,
      "MEASURED",
      10,
      3.0
    ],
    [
      1770067260000,
      "MEASURED",
      10,
      3.0
    ],
    [
      1770067440000,
      "MEASURED",
      10,
      3.0
    ],
    [
      1770067620000,
      "MEASURED",
      10,
      3.0
    ],
    [
      1770067800000,
      "MEASURED",
      10,
      3.0
    ],
    [
      1770067980000,
      "MEASURED",
      10,
      3.0
    ],
    [
      1770068160000,
      "MEASURED",
      10,
      3.0
    ],
    [
      1770068340000,
      "MEASURED",
      9,
      3.0
    ],
    [
      1770068520000,
      "MEASURED",
      9,
      3.0
    ],
    [
      1770068700000,
      "MEASURED",
      9,
      3.0
    ],
    [
      1770068880000,
      "MEASURED",
      9,
      3.0
    ],
    [
      1770069060000,
      "MEASURED",
      9,
      3.0
    ],
    [
      1770069240000,
      "MEASURED",
      9,
      3.0
    ],
    [
      1770069420000,
      "MEASURED",
      9,
      3.0
    ],
    [
      1770069600000,
      "MEASURED",
      9,
      3.0
    ],
    [
      1770069780000,
      "MEASURED",
      9,
      3.0
    ],
    [
      1770069960000,
      "MEASURED",
      9,
      3.0
    ],
    [
      1770070140000,
      "MEASURED",
      9,
      3.0
    ],
    [
      1770070320000,
      "MEASURED",
      9,
      3.0
    ],
    [
      1770070500000,
      "MEASURED",
      9,
      3.0
    ],
    [
      1770070680000,
      "MEASURED",
      8,
      3.0
    ],
    [
      1770070860000,
      "MEASURED",
      8,
      3.0
    ],
    [
      1770071040000,
      "MEASURED",
      8,
      3.0
    ],
    [
      1770071220000,
      "MEASURED",
      8,
      3.0
    ],
    [
      1770071400000,
      "MEASURED",
      8,
      3.0
    ],
    [
      1770071580000,
      "MEASURED",
      8,
      3.0
    ],
    [
      1770071760000,
      "MEASURED",
      8,
      3.0
    ],
    [
      1770071940000,
      "MEASURED",
      8,
      3.0
    ],
    [
      1770072120000,
      "MEASURED",
      8,
      3.0
    ],
    [
      1770072300000,
      "MEASURED",
      8,
      3.0
    ],
    [
      1770072480000,
      "MEASURED",
      8,
      3.0
    ],
    [
      1770072660000,
      "MEASURED",
      8,
      3.0
    ],
    [
      1770072840000,
      "MEASURED",
      8,
      3.0
    ],
    [
      1770073020000,
      "MEASURED",
      8,
      3.0
    ],
    [
      1770073200000,
      "MEASURED",
      8,
      3.0
    ],
    [
      1770073380000,
      "MEASURED",
      8,
      3.0
    ],
    [
      1770073560000,
      "MEASURED",
      8,
      3.0
    ],
    [
      1770073740000,
      "MEASURED",
      10,
      3.0
    ],
    [
      1770073920000,
      "MEASURED",
      10,
      3.0
    ],
    [
      1770074100000,
      "MEASURED",
      10,
      3.0
    ],
    [
      1770074280000,
      "MEASURED",
      10,
      3.0
    ],
    [
      1770074460000,
      "MEASURED",
      11,
      3.0
    ],
    [
      1770074640000,
      "MEASURED",
      11,
      3.0
    ],
    [
      1770074820000,
      "MEASURED",
      11,
      3.0
    ],
    [
      1770075000000,
      "MEASURED",
      12,
      3.0
    ],
    [
      1770075180000,
      "MEASURED",
      12,
      3.0
    ],
    [
      1770075360000,
      "MEASURED",
      13,
      3.0
    ],
    [
      1770075540000,
      "MEASURED",
      13,
      3.0
    ],
    [
      1770075720000,
      "MEASURED",
      14,
      3.0
    ],
    [
      1770075900000,
      "MEASURED",
      14,
      3.0
    ],
    [
      1770076080000,
      "MEASURED",
      15,
      3.0
    ],
    [
      1770076260000,
      "MEASURED",
      15,
      3.0
    ],
    [
      1770076440000,
      "MEASURED",
      15,
      3.0
    ],
    [
      1770076620000,
      "MEASURED",
      16,
      3.0
    ],
    [
      1770076800000,
      "MEASURED",
      16,
      3.0
    ],
    [
      1770076980000,
      "MEASURED",
      16,
      3.0
    ],
    [
      1770077160000,
      "MEASURED",
      17,
      3.0
    ],
    [
      1770077340000,
      "MEASURED",
      17,
      3.0
    ],
    [
      1770077520000,
      "MEASURED",
      17,
      3.0
    ],
    [
      1770077700000,
      "MEASURED",
      18,
      3.0
    ],
    [
      1770077880000,
      "MEASURED",
      18,
      3.0
    ],
    [
      1770078060000,
      "MEASURED",
      20,
      3.0
    ],
    [
      1770078240000,
      "MEASURED",
      20,
      3.0
    ],
    [
      1770078420000,
      "MEASURED",
      21,
      3.0
    ],
    [
      1770078600000,
      "MEASURED",
      21,
      3.0
    ],
    [
      1770078780000,
      "MEASURED",
      22,
      3.0
    ],
    [
      1770078960000,
      "MEASURED",
      23,
      3.0
    ],
    [
      1770079140000,
      "MEASURED",
      23,
      3.0
    ],
    [
      1770079320000,
      "MEASURED",
      24,
      3.0
    ],
    [
      1770079500000,
      "MEASURED",
      25,
      3.0
    ],
    [
      1770079680000,
      "MEASURED",
      25,
      3.0
    ],
    [
      1770079860000,
      "MEASURED",
      26,
      3.0
    ],
    [
      1770080040000,
      "MEASURED",
      27,
      3.0
    ],
    [
      1770080220000,
      "MEASURED",
      28,
      3.0
    ],
    [
      1770080400000,
      "MEASURED",
      28,
      3.0
    ],
    [
      1770080580000,
      "MEASURED",
      29,
      3.0
    ],
    [
      1770080760000,
      "MEASURED",
      30,
      3.0
    ],
    [
      1770080940000,
      "MEASURED",
      31,
      3.0
    ],
    [
      1770081120000,
      "MEASURED",
      32,
      3.0
    ],
    [
      1770081300000,
      "MEASURED",
      33,
      3.0
    ],
    [
      1770081480000,
      "MEASURED",
      33,
      3.0
    ],
    [
      1770081660000,
      "MEASURED",
      35,
      3.0
    ],
    [
      1770081840000,
      "MEASURED",
      36,
      3.0
    ],
    [
      1770082020000,
      "MEASURED",
      37,
      3.0
    ],
    [
      1770082200000,
      "MEASURED",
      37,
      3.0
    ],
    [
      1770082380000,
      "MEASURED",
      38,
      3.0
    ],
    [
      1770082560000,
      "MEASURED",
      38,
      3.0
    ],
    [
      1770082740000,
      "MEASURED",
      39,
      3.0
    ],
    [
      1770082920000,
      "MEASURED",
      39,
      3.0
    ],
    [
      1770083100000,
      "MEASURED",
      40,
      3.0
    ],
    [
      1770083280000,
      "MEASURED",
      41,
      3.0
    ],
    [
      1770083460000,
      "MEASURED",
      41,
      3.0
    ],
    [
      1770083640000,
      "MEASURED",
      43,
      3.0
    ],
    [
      1770083820000,
      "MEASURED",
      43,
      3.0
    ],
    [
      1770084000000,
      "MEASURED",
      44,
      3.0
    ],
    [
      1770084180000,
      "MEASURED",
      45,
      3.0
    ],
    [
      1770084360000,
      "MEASURED",
      46,
      3.0
    ],
    [
      1770084540000,
      "MEASURED",
      46,
      3.0
    ],
    [
      1770084720000,
      "MEASURED",
      48,
      3.0
    ],
    [
      1770084900000,
      "MEASURED",
      48,
      3.0
    ],
    [
      1770085080000,
      "MEASURED",
      49,
      3.0
    ],
    [
      1770085260000,
      "MEASURED",
      50,
      3.0
    ],
    [
      1770085440000,
      "MEASURED",
      50,
      3.0
    ],
    [
      1770085620000,
      "MEASURED",
      51,
      3.0
    ],
    [
      1770085800000,
      "MEASURED",
      51,
      3.0
    ],
    [
      1770085980000,
      "MEASURED",
      52,
      3.0
    ],
    [
      1770086160000,
      "MEASURED",
      53,
      3.0
    ],
    [
      1770086340000,
      "MEASURED",
      53,
      3.0
    ],
    [
      1770086520000,
      "MEASURED",
      54,
      3.0
    ],
    [
      1770086700000,
      "MEASURED",
      55,
      3.0
    ],
    [
      1770086880000,
      "MEASURED",
      55,
      3.0
    ],
    [
      1770087060000,
      "MEASURED",
      55,
      3.0
    ],
    [
      1770087240000,
      "MEASURED",
      55,
      3.0
    ],
    [
      1770087420000,
      "MEASURED",
      56,
      3.0
    ],
    [
      1770087600000,
      "MEASURED",
      57,
      3.0
    ],
    [
      1770087780000,
      "MEASURED",
      57,
      3.0
    ],
    [
      1770087960000,
      "MEASURED",
      57,
      3.0
    ],
    [
      1770088140000,
      "MEASURED",
      58,
      3.0
    ],
    [
      1770088320000,
      "MEASURED",
      59,
      3.0
    ],
    [
      1770088500000,
      "MEASURED",
      60,
      3.0
    ],
    [
      1770088680000,
      "MEASURED",
      61,
      3.0
    ],
    [
      1770088860000,
      "MEASURED",
      61,
      3.0
    ],
    [
      1770089040000,
      "MEASURED",
      62,
      3.0
    ],
    [
      1770089220000,
      "MEASURED",
      62,
      3.0
    ],
    [
      1770089400000,
      "MEASURED",
      63,
      3.0
    ],
    [
      1770089580000,
      "MEASURED",
      64,
      3.0
    ],
    [
      1770089760000,
      "MEASURED",
      65,
      3.0
    ],
    [
      1770089940000,
      "MEASURED",
      65,
      3.0
    ],
    [
      1770090120000,
      "MEASURED",
      66,
      3.0
    ],
    [
      1770090300000,
      "MEASURED",
      66,
      3.0
    ],
    [
      1770090480000,
      "MEASURED",
      67,
      3.0
    ],
    [
      1770090660000,
      "MEASURED",
      68,
      3.0
    ],
    [
      1770090840000,
      "MEASURED",
      69,
      3.0
    ],
    [
      1770091020000,
      "MEASURED",
      69,
      3.0
    ],
    [
      1770091200000,
      "MEASURED",
      70,
      3.0
    ],
    [
      1770091380000,
      "MEASURED",
      70,
      3.0
    ],
    [
      1770091560000,
      "MEASURED",
      71,
      3.0
    ],
    [
      1770091740000,
      "MEASURED",
      71,
      3.0
    ],
    [
      1770091920000,
      "MEASURED",
      72,
      3.0
    ],
    [
      1770092100000,
      "MEASURED",
      73,
      3.0
    ],
    [
      1770092280000,
      "MEASURED",
      73,
      3.0
    ],
    [
      1770092460000,
      "MEASURED",
      73,
      3.0
    ],
    [
      1770092640000,
      "MEASURED",
      74,
      3.0
    ],
    [
      1770092820000,
      "MEASURED",
      74,
      3.0
    ],
    [
      1770093000000,
      "MEASURED",
      75,
      3.0
    ],
    [
      1770093180000,
      "MEASURED",
      75,
      3.0
    ],
    [
      1770093360000,
      "MEASURED",
      75,
      3.0
    ],
    [
      1770093540000,
      "MEASURED",
      76,
      3.0
    ],
    [
      1770093720000,
      "MEASURED",
      77,
      3.0
    ],
    [
      1770093900000,
      "MEASURED",
      77,
      3.0
    ],
    [
      1770094080000,
      "MEASURED",
      77,
      3.0
    ],
    [
      1770094260000,
      "MEASURED",
      77,
      3.0
    ],
    [
      1770094440000,
      "MEASURED",
      78,
      3.0
    ],
    [
      1770094620000,
      "MEASURED",
      78,
      3.0
    ],
    [
      1770094800000,
      "MEASURED",
      79,
      3.0
    ],
    [
      1770094980000,
      "MEASURED",
      80,
      3.0
    ],
    [
      1770095160000,
      "MEASURED",
      80,
      3.0
    ],
    [
      1770095340000,
      "MEASURED",
      81,
      3.0
    ],
    [
      1770095520000,
      "MEASURED",
      81,
      3.0
    ],
    [
      1770095700000,
      "MEASURED",
      81,
      3.0
    ],
    [
      1770095880000,
      "MEASURED",
      82,
      3.0
    ],
    [
      1770096060000,
      "MEASURED",
      82,
      3.0
    ],
    [
      1770096240000,
      "MEASURED",
      82,
      3.0
    ],
    [
      1770096420000,
      "MEASURED",
      83,
      3.0
    ],
    [
      1770096600000,
      "MEASURED",
      84,
      3.0
    ],
    [
      1770096780000,
      "MEASURED",
      84,
      3.0
    ],
    [
      1770096960000,
      "MEASURED",
      85,
      3.0
    ],
    [
      1770097140000,
      "MEASURED",
      85,
      3.0
    ],
    [
      1770097320000,
      "MEASURED",
      85,
      3.0
    ],
    [
      1770097500000,
      "MEASURED",
      85,
      3.0
    ],
    [
      1770097680000,
      "MEASURED",
      85,
      3.0
    ],
    [
      1770097860000,
      "MEASURED",
      85,
      3.0
    ],
    [
      1770098040000,
      "MEASURED",
      86,
      3.0
    ],
    [
      1770098220000,
      "MEASURED",
      86,
      3.0
    ],
    [
      1770098400000,
      "MEASURED",
      87,
      3.0
    ],
    [
      1770098580000,
      "MEASURED",
      87,
      3.0
    ],
    [
      1770098760000,
      "MEASURED",
      87,
      3.0
    ],
    [
      1770098940000,
      "MEASURED",
      87,
      3.0
    ],
    [
      1770099120000,
      "MEASURED",
      88,
      3.0
    ],
    [
      1770099300000,
      "MEASURED",
      88,
      3.0
    ],
    [
      1770099480000,
      "MEASURED",
      88,
      3.0
    ],
    [
      1770099660000,
      "MEASURED",
      88,
      3.0
    ],
    [
      1770099840000,
      "MEASURED",
      88,
      3.0
    ],
    [
      1770100020000,
      "MEASURED",
      88,
      3.0
    ],
    [
      1770100200000,
      "MEASURED",
      89,
      3.0
    ],
    [
      1770100380000,
      "MEASURED",
      89,
      3.0
    ],
    [
      1770100560000,
      "MEASURED",
      90,
      3.0
    ],
    [
      1770100740000,
      "MEASURED",
      90,
      3.0
    ],
    [
      1770100920000,
      "MEASURED",
      90,
      3.0
    ],
    [
      1770101100000,
      "MEASURED",
      90,
      3.0
    ],
    [
      1770101280000,
      "MEASURED",
      91,
      3.0
    ],
    [
      1770101460000,
      "MEASURED",
      91,
      3.0
    ],
    [
      1770101640000,
      "MEASURED",
      91,
      3.0
    ],
    [
      1770101820000,
      "MEASURED",
      92,
      3.0
    ],
    [
      1770102000000,
      "MEASURED",
      92,
      3.0
    ],
    [
      1770102180000,
      "MEASURED",
      92,
      3.0
    ],
    [
      1770102360000,
      "MEASURED",
      93,
      3.0
    ],
    [
      1770102540000,
      "MEASURED",
      93,
      3.0
    ],
    [
      1770102720000,
      "MEASURED",
      93,
      3.0
    ],
    [
      1770102900000,
      "MEASURED",
      93,
      3.0
    ],
    [
      1770103080000,
      "MEASURED",
      93,
      3.0
    ],
    [
      1770103260000,
      "MEASURED",
      93,
      3.0
    ],
    [
      1770103440000,
      "MEASURED",
      92,
      3.0
    ],
    [
      1770103620000,
      "MEASURED",
      92,
      3.0
    ],
    [
      1770103800000,
      "MEASURED",
      92,
      3.0
    ],
    [
      1770103980000,
      "MEASURED",
      91,
      3.0
    ],
    [
      1770104160000,
      "MEASURED",
      91,
      3.0
    ],
    [
      1770104340000,
      "MEASURED",
      91,
      3.0
    ],
    [
      1770104520000,
      "MEASURED",
      91,
      3.0
    ],
    [
      1770104700000,
      "MEASURED",
      91,
      3.0
    ],
    [
      1770104880000,
      "MEASURED",
      91,
      3.0
    ],
    [
      1770105060000,
      "MEASURED",
      91,
      3.0
    ],
    [
      1770105240000,
      "MEASURED",
      91,
      3.0
    ],
    [
      1770105420000,
      "MEASURED",
      90,
      3.0
    ],
    [
      1770105600000,
      "MEASURED",
      89,
      3.0
    ],
    [
      1770105780000,
      "MEASURED",
      89,
      3.0
    ],
    [
      1770105960000,
      "MEASURED",
      89,
      3.0
    ],
    [
      1770106140000,
      "MEASURED",
      89,
      3.0
    ],
    [
      1770106320000,
      "MEASURED",
      89,
      3.0
    ],
    [
      1770106500000,
      "MEASURED",
      88,
      3.0
    ],
    [
      1770106680000,
      "MEASURED",
      88,
      3.0
    ],
    [
      1770106860000,
      "MEASURED",
      88,
      3.0
    ],
    [
      1770107040000,
      "MEASURED",
      87,
      3.0
    ],
    [
      1770107220000,
      "MEASURED",
      87,
      3.0
    ],
    [
      1770107400000,
      "MEASURED",
      87,
      3.0
    ],
    [
      1770107580000,
      "MEASURED",
      86,
      3.0
    ],
    [
      1770107760000,
      "MEASURED",
      86,
      3.0
    ],
    [
      1770107940000,
      "MEASURED",
      86,
      3.0
    ],
    [
      1770108120000,
      "MEASURED",
      86,
      3.0
    ],
    [
      1770108300000,
      "MEASURED",
      85,
      3.0
    ],
    [
      1770108480000,
      "MEASURED",
      85,
      3.0
    ],
    [
      1770108660000,
      "MEASURED",
      85,
      3.0
    ],
    [
      1770108840000,
      "MEASURED",
      85,
      3.0
    ],
    [
      1770109020000,
      "MEASURED",
      85,
      3.0
    ],
    [
      1770109200000,
      "MEASURED",
      84,
      3.0
    ],
    [
      1770109380000,
      "MEASURED",
      84,
      3.0
    ],
    [
      1770109560000,
      "MEASURED",
      84,
      3.0
    ],
    [
      1770109740000,
      "MEASURED",
      83,
      3.0
    ],
    [
      1770109920000,
      "MEASURED",
      83,
      3.0
    ],
    [
      1770110100000,
      "MEASURED",
      83,
      3.0
    ],
    [
      1770110280000,
      "MEASURED",
      83,
      3.0
    ],
    [
      1770110460000,
      "MEASURED",
      83,
      3.0
    ],
    [
      1770110640000,
      "MEASURED",
      83,
      3.0
    ],
    [
      1770110820000,
      "MEASURED",
      83,
      3.0
    ],
    [
      1770111000000,
      "MEASURED",
      83,
      3.0
    ],
    [
      1770111180000,
      "MEASURED",
      83,
      3.0
    ],
    [
      1770111360000,
      "MEASURED",
      83,
      3.0
    ],
    [
      1770111540000,
      "MEASURED",
      82,
      3.0
    ],
    [
      1770111720000,
      "MEASURED",
      82,
      3.0
    ],
    [
      1770111900000,
      "MEASURED",
      82,
      3.0
    ],
    [
      1770112080000,
      "MEASURED",
      81,
      3.0
    ],
    [
      1770112260000,
      "MEASURED",
      81,
      3.0
    ],
    [
      1770112440000,
      "MEASURED",
      80,
      3.0
    ],
    [
      1770112620000,
      "MEASURED",
      80,
      3.0
    ],
    [
      1770112800000,
      "MEASURED",
      80,
      3.0
    ],
    [
      1770112980000,
      "MEASURED",
      80,
      3.0
    ],
    [
      1770113160000,
      "MEASURED",
      80,
      3.0
    ],
    [
      1770113340000,
      "MEASURED",
      79,
      3.0
    ],
    [
      1770113520000,
      "MEASURED",
      79,
      3.0
    ],
    [
      1770113700000,
      "MEASURED",
      79,
      3.0
    ],
    [
      1770113880000,
      "MEASURED",
      78,
      3.0
    ],
    [
      1770114060000,
      "MEASURED",
      78,
      3.0
    ],
    [
      1770114240000,
      "MEASURED",
      78,
      3.0
    ],
    [
      1770114420000,
      "MEASURED",
      77,
      3.0
    ],
    [
      1770114600000,
      "MEASURED",
      76,
      3.0
    ],
    [
      1770114780000,
      "MEASURED",
      76,
      3.0
    ],
    [
      1770114960000,
      "MEASURED",
      76,
      3.0
    ],
    [
      1770115140000,
      "MEASURED",
      75,
      3.0
    ],
    [
      1770115320000,
      "MEASURED",
      75,
      3.0
    ],
    [
      1770115500000,
      "MEASURED",
      74,
      3.0
    ],
    [
      1770115680000,
      "MEASURED",
      74,
      3.0
    ],
    [
      1770115860000,
      "MEASURED",
      73,
      3.0
    ],
    [
      1770116040000,
      "MEASURED",
      73,
      3.0
    ],
    [
      1770116220000,
      "MEASURED",
      73,
      3.0
    ],
    [
      1770116400000,
      "MEASURED",
      72,
      3.0
    ],
    [
      1770116580000,
      "MEASURED",
      72,
      3.0
    ],
    [
      1770116760000,
      "MEASURED",
      71,
      3.0
    ],
    [
      1770116940000,
      "MEASURED",
      71,
      3.0
    ],
    [
      1770117120000,
      "MEASURED",
      71,
      3.0
    ],
    [
      1770117300000,
      "MEASURED",
      71,
      3.0
    ],
    [
      1770117480000,
      "MEASURED",
      70,
      3.0
    ],
    [
      1770117660000,
      "MEASURED",
      70,
      3.0
    ],
    [
      1770117840000,
      "MEASURED",
      69,
      3.0
    ],
    [
      1770118020000,
      "MEASURED",
      69,
      3.0
    ],
    [
      1770118200000,
      "MEASURED",
      69,
      3.0
    ],
    [
      1770118380000,
      "MEASURED",
      69,
      3.0
    ],
    [
      1770118560000,
      "MEASURED",
      68,
      3.0
    ],
    [
      1770118740000,
      "MEASURED",
      68,
      3.0
    ],
    [
      1770118920000,
      "MEASURED",
      68,
      3.0
    ],
    [
      1770119100000,
      "MEASURED",
      67,
      3.0
    ],
    [
      1770119280000,
      "MEASURED",
      67,
      3.0
    ],
    [
      1770119460000,
      "MEASURED",
      67,
      3.0
    ],
    [
      1770119640000,
      "MEASURED",
      66,
      3.0
    ],
    [
      1770119820000,
      "MEASURED",
      66,
      3.0
    ],
    [
      1770120000000,
      "MEASURED",
      66,
      3.0
    ],
    [
      1770120180000,
      "MEASURED",
      66,
      3.0
    ],
    [
      1770120360000,
      "MEASURED",
      66,
      3.0
    ],
    [
      1770120540000,
      "MEASURED",
      65,
      3.0
    ],
    [
      1770120720000,
      "MEASURED",
      65,
      3.0
    ],
    [
      1770120900000,
      "MEASURED",
      64,
      3.0
    ],
    [
      1770121080000,
      "MEASURED",
      64,
      3.0
    ],
    [
      1770121260000,
      "MEASURED",
      64,
      3.0
    ],
    [
      1770121440000,
      "MEASURED",
      64,
      3.0
    ],
    [
      1770121620000,
      "MEASURED",
      63,
      3.0
    ],
    [
      1770121800000,
      "MEASURED",
      63,
      3.0
    ],
    [
      1770121980000,
      "MEASURED",
      63,
      3.0
    ],
    [
      1770122160000,
      "MEASURED",
      62,
      3.0
    ],
    [
      1770122340000,
      "MEASURED",
      61,
      3.0
    ],
    [
      1770122520000,
      "MEASURED",
      61,
      3.0
    ],
    [
      1770122700000,
      "MEASURED",
      61,
      3.0
    ],
    [
      1770122880000,
      "MEASURED",
      61,
      3.0
    ],
    [
      1770123060000,
      "MEASURED",
      60,
      3.0
    ],
    [
      1770123240000,
      "MEASURED",
      60,
      3.0
    ],
    [
      1770123420000,
      "MEASURED",
      60,
      3.0
    ],
    [
      1770123600000,
      "MEASURED",
      59,
      3.0
    ],
    [
      1770123780000,
      "MEASURED",
      59,
      3.0
    ],
    [
      1770123960000,
      "MEASURED",
      59,
      3.0
    ],
    [
      1770124140000,
      "MEASURED",
      59,
      3.0
    ],
    [
      1770124320000,
      "MEASURED",
      58,
      3.0
    ],
    [
      1770124500000,
      "MEASURED",
      58,
      3.0
    ],
    [
      1770124680000,
      "MEASURED",
      57,
      3.0
    ],
    [
      1770124860000,
      "MEASURED",
      57,
      3.0
    ],
    [
      1770125040000,
      "MEASURED",
      57,
      3.0
    ],
    [
      1770125220000,
      "MEASURED",
      56,
      3.0
    ],
    [
      1770125400000,
      "MEASURED",
      56,
      3.0
    ],
    [
      1770125580000,
      "MEASURED",
      55,
      3.0
    ],
    [
      1770125760000,
      "MEASURED",
      55,
      3.0
    ],
    [
      1770125940000,
      "MEASURED",
      55,
      3.0
    ],
    [
      1770126120000,
      "MEASURED",
      55,
      3.0
    ],
    [
      1770126300000,
      "MEASURED",
      55,
      3.0
    ],
    [
      1770126480000,
      "MEASURED",
      54,
      3.0
    ],
    [
      1770126660000,
      "MEASURED",
      54,
      3.0
    ],
    [
      1770126840000,
      "MEASURED",
      54,
      3.0
    ],
    [
      1770127020000,
      "MEASURED",
      54,
      3.0
    ],
    [
      1770127200000,
      "MEASURED",
      54,
      3.0
    ],
    [
      1770127380000,
      "MEASURED",
      53,
      3.0
    ],
    [
      1770127560000,
      "MEASURED",
      53,
      3.0
    ],
    [
      1770127740000,
      "MEASURED",
      53,
      3.0
    ],
    [
      1770127920000,
      "MEASURED",
      53,
      3.0
    ],
    [
      1770128100000,
      "MEASURED",
      52,
      3.0
    ],
    [
      1770128280000,
      "MEASURED",
      52,
      3.0
    ],
    [
      1770128460000,
      "MEASURED",
      52,
      3.0
    ],
    [
      1770128640000,
      "MEASURED",
      51,
      3.0
    ],
    [
      1770128820000,
      "MEASURED",
      51,
      3.0
    ],
    [
      1770129000000,
      "MEASURED",
      51,
      3.0
    ],
    [
      1770129180000,
      "MEASURED",
      51,
      3.0
    ],
    [
      1770129360000,
      "MEASURED",
      50,
      3.0
    ],
    [
      1770129540000,
      "MEASURED",
      50,
      3.0
    ],
    [
      1770129720000,
      "MEASURED",
      50,
      3.0
    ],
    [
      1770129900000,
      "MEASURED",
      50,
      3.0
    ],
    [
      1770130080000,
      "MEASURED",
      49,
      3.0
    ],
    [
      1770130260000,
      "MEASURED",
      49,
      3.0
    ],
    [
      1770130440000,
      "MEASURED",
      49,
      3.0
    ],
    [
      1770130620000,
      "MEASURED",
      48,
      3.0
    ],
    [
      1770130800000,
      "MEASURED",
      47,
      3.0
    ],
    [
      1770130980000,
      "MEASURED",
      47,
      3.0
    ],
    [
      1770131160000,
      "MEASURED",
      47,
      3.0
    ],
    [
      1770131340000,
      "MEASURED",
      47,
      3.0
    ],
    [
      1770131520000,
      "MEASURED",
      46,
      3.0
    ],
    [
      1770131700000,
      "MEASURED",
      46,
      3.0
    ],
    [
      1770131880000,
      "MEASURED",
      46,
      3.0
    ],
    [
      1770132060000,
      "MEASURED",
      46,
      3.0
    ],
    [
      1770132240000,
      "MEASURED",
      46,
      3.0
    ],
    [
      1770132420000,
      "MEASURED",
      46,
      3.0
    ],
    [
      1770132600000,
      "MEASURED",
      46,
      3.0
    ],
    [
      1770132780000,
      "MEASURED",
      46,
      3.0
    ],
    [
      1770132960000,
      "MEASURED",
      46,
      3.0
    ],
    [
      1770133140000,
      "MEASURED",
      46,
      3.0
    ],
    [
      1770133320000,
      "MEASURED",
      45,
      3.0
    ],
    [
      1770133500000,
      "MEASURED",
      45,
      3.0
    ],
    [
      1770133680000,
      "MEASURED",
      45,
      3.0
    ],
    [
      1770133860000,
      "MEASURED",
      44,
      3.0
    ],
    [
      1770134040000,
      "MEASURED",
      44,
      3.0
    ],
    [
      1770134220000,
      "MEASURED",
      44,
      3.0
    ],
    [
      1770134400000,
      "MEASURED",
      44,
      3.0
    ],
    [
      1770134580000,
      "MEASURED",
      43,
      3.0
    ],
    [
      1770134760000,
      "MEASURED",
      43,
      3.0
    ],
    [
      1770134940000,
      "MEASURED",
      43,
      3.0
    ],
    [
      1770135120000,
      "MEASURED",
      43,
      3.0
    ],
    [
      1770135300000,
      "MEASURED",
      43,
      3.0
    ],
    [
      1770135480000,
      "MEASURED",
      43,
      3.0
    ],
    [
      1770135660000,
      "MEASURED",
      43,
      3.0
    ],
    [
      1770135840000,
      "MEASURED",
      43,
      3.0
    ],
    [
      1770136020000,
      "MEASURED",
      43,
      3.0
    ],
    [
      1770136200000,
      "MEASURED",
      43,
      3.0
    ],
    [
      1770136380000,
      "MEASURED",
      42,
      3.0
    ],
    [
      1770136560000,
      "MEASURED",
      41,
      3.0
    ],
    [
      1770136740000,
      "MEASURED",
      41,
      3.0
    ],
    [
      1770136920000,
      "MEASURED",
      41,
      3.0
    ],
    [
      1770137100000,
      "MEASURED",
      41,
      3.0
    ],
    [
      1770137280000,
      "MEASURED",
      41,
      3.0
    ],
    [
      1770137460000,
      "MEASURED",
      41,
      3.0
    ],
    [
      1770137640000,
      "MEASURED",
      41,
      3.0
    ],
    [
      1770137820000,
      "MEASURED",
      41,
      3.0
    ],
    [
      1770138000000,
      "MEASURED",
      41,
      3.0
    ],
    [
      1770138180000,
      "MEASURED",
      41,
      3.0
    ],
    [
      1770138360000,
      "MEASURED",
      40,
      3.0
    ],
    [
      1770138540000,
      "MEASURED",
      40,
      3.0
    ],
    [
      1770138720000,
      "MEASURED",
      40,
      3.0
    ],
    [
      1770138900000,
      "MEASURED",
      40,
      3.0
    ],
    [
      1770139080000,
      "MEASURED",
      39,
      3.0
    ],
    [
      1770139260000,
      "MEASURED",
      39,
      3.0
    ],
    [
      1770139440000,
      "MEASURED",
      39,
      3.0
    ],
    [
      1770139620000,
      "MEASURED",
      39,
      3.0
    ],
    [
      1770139800000,
      "MEASURED",
      39,
      3.0
    ],
    [
      1770139980000,
      "MEASURED",
      39,
      3.0
    ],
    [
      1770140160000,
      "MEASURED",
      39,
      3.0
    ],
    [
      1770140340000,
      "MEASURED",
      38,
      3.0
    ],
    [
      1770140520000,
      "MEASURED",
      38,
      3.0
    ],
    [
      1770140700000,
      "MEASURED",
      38,
      3.0
    ],
    [
      1770140880000,
      "MEASURED",
      38,
      3.0
    ],
    [
      1770141060000,
      "MEASURED",
      38,
      3.0
    ],
    [
      1770141240000,
      "MEASURED",
      38,
      3.0
    ],
    [
      1770141420000,
      "MEASURED",
      38,
      3.0
    ],
    [
      1770141600000,
      "MEASURED",
      38,
      3.0
    ],
    [
      1770141780000,
      "MEASURED",
      38,
      3.0
    ],
    [
      1770141960000,
      "MEASURED",
      38,
      3.0
    ],
    [
      1770142140000,
      "MEASURED",
      38,
      3.0
    ],
    [
      1770142320000,
      "MEASURED",
      37,
      3.0
    ],
    [
      1770142500000,
      "MEASURED",
      37,
      3.0
    ],
    [
      1770142680000,
      "MEASURED",
      37,
      3.0
    ],
    [
      1770142860000,
      "MEASURED",
      37,
      3.0
    ],
    [
      1770143040000,
      "MEASURED",
      36,
      3.0
    ],
    [
      1770143220000,
      "MEASURED",
      36,
      3.0
    ],
    [
      1770143400000,
      "MEASURED",
      36,
      3.0
    ],
    [
      1770143580000,
      "MEASURED",
      36,
      3.0
    ],
    [
      1770143760000,
      "MEASURED",
      36,
      3.0
    ],
    [
      1770143940000,
      "MEASURED",
      35,
      3.0
    ],
    [
      1770144120000,
      "MEASURED",
      35,
      3.0
    ],
    [
      1770144300000,
      "MEASURED",
      35,
      3.0
    ],
    [
      1770144480000,
      "MEASURED",
      34,
      3.0
    ],
    [
      1770144660000,
      "MEASURED",
      33,
      3.0
    ],
    [
      1770144840000,
      "MEASURED",
      33,
      3.0
    ],
    [
      1770145020000,
      "MEASURED",
      33,
      3.0
    ],
    [
      1770145200000,
      "MEASURED",
      33,
      3.0
    ],
    [
      1770145380000,
      "MEASURED",
      32,
      3.0
    ],
    [
      1770145560000,
      "MEASURED",
      32,
      3.0
    ],
    [
      1770145740000,
      "MEASURED",
      32,
      3.0
    ],
    [
      1770145920000,
      "MEASURED",
      32,
      3.0
    ],
    [
      1770146100000,
      "MEASURED",
      31,
      3.0
    ],
    [
      1770146280000,
      "MEASURED",
      31,
      3.0
    ],
    [
      1770146460000,
      "MEASURED",
      31,
      3.0
    ],
    [
      1770146640000,
      "MEASURED",
      31,
      3.0
    ],
    [
      1770146820000,
      "MEASURED",
      31,
      3.0
    ],
    [
      1770147000000,
      "MEASURED",
      31,
      3.0
    ],
    [
      1770147180000,
      "MEASURED",
      31,
      3.0
    ],
    [
      1770147360000,
      "MEASURED",
      30,
      3.0
    ],
    [
      1770147540000,
      "MEASURED",
      30,
      3.0
    ],
    [
      1770147720000,
      "MEASURED",
      30,
      3.0
    ],
    [
      1770147900000,
      "MEASURED",
      30,
      3.0
    ],
    [
      1770148080000,
      "MEASURED",
      30,
      3.0
    ],
    [
      1770148260000,
      "MEASURED",
      30,
      3.0
    ],
    [
      1770148440000,
      "MEASURED",
      29,
      3.0
    ],
    [
      1770148620000,
      "MEASURED",
      29,
      3.0
    ],
    [
      1770148800000,
      "MEASURED",
      29,
      3.0
    ],
    [
      1770148980000,
      "MEASURED",
      29,
      3.0
    ],
    [
      1770149160000,
      "MEASURED",
      29,
      3.0
    ],
    [
      1770149340000,
      "MEASURED",
      29,
      3.0
    ],
    [
      1770149520000,
      "MEASURED",
      29,
      3.0
    ],
    [
      1770149700000,
      "MEASURED",
      29,
      3.0
    ],
    [
      1770149880000,
      "MEASURED",
      29,
      3.0
    ],
    [
      1770150060000,
      "MEASURED",
      28,
      3.0
    ],
    [
      1770150240000,
      "MEASURED",
      28,
      3.0
    ],
    [
      1770150420000,
      "MEASURED",
      28,
      3.0
    ],
    [
      1770150600000,
      "MEASURED",
      28,
      3.0
    ],
    [
      1770150780000,
      "MEASURED",
      28,
      3.0
    ],
    [
      1770150960000,
      "MEASURED",
      28,
      3.0
    ],
    [
      1770151140000,
      "MEASURED",
      28,
      3.0
    ],
    [
      1770151320000,
      "MEASURED",
      28,
      3.0
    ],
    [
      1770151500000,
      "MEASURED",
      28,
      3.0
    ],
    [
      1770151680000,
      "MEASURED",
      27,
      3.0
    ],
    [
      1770151860000,
      "MEASURED",
      27,
      3.0
    ],
    [
      1770152040000,
      "MEASURED",
      27,
      3.0
    ],
    [
      1770152220000,
      "MEASURED",
      27,
      3.0
    ]
  ]
}